setup.cfg
setup.py
gaq_hub/__init__.py
gaq_hub/pylons_helpers.py
gaq_hub/pyramid_helpers.py
gaq_hub.egg-info/PKG-INFO
gaq_hub.egg-info/SOURCES.txt
gaq_hub.egg-info/dependency_links.txt
gaq_hub.egg-info/not-zip-safe
gaq_hub.egg-info/requires.txt
gaq_hub.egg-info/top_level.txt