Metadata-Version: 1.1
Name: gaq-hub
Version: 0.0.13
Summary: Lightweight Google Analytics support
Home-page: https://github.com/jvanasco/gaq_hub
Author: Jonathan Vanasco
Author-email: jonathan@findmeon.com
License: MIT
Keywords: web pylons
Platform: UNKNOWN
Classifier: Intended Audience :: Developers
Classifier: Framework :: Pylons
Classifier: Framework :: Pyramid
Classifier: Programming Language :: Python
Classifier: License :: OSI Approved :: MIT License
